{
  "project_info": {
    "project_number": "913254759526",
    "project_id": "sws-ai-chat",
    "storage_bucket": "sws-ai-chat.firebasestorage.app"
  },
  "client": [
    {
      "client_info": {
        "mobilesdk_app_id": "1:913254759526:android:1600319d8bc24af648c1a7",
        "android_client_info": {
          "package_name": "com.example.sws_ai"
        }
      },
      "oauth_client": [],
      "api_key": [
        {
          "current_key": "AIzaSyAY29WNttMkzbDKNH0IoOPRRs76NwAMPOE"
        }
      ],
      "services": {
        "appinvite_service": {
          "other_platform_oauth_client": []
        }
      }
    }
  ],
  "configuration_version": "1"
}